izok/__init__.py
izok/ast.py
izok/ast_est.py
izok/baseparser.py
izok/basescaner.py
izok/error.py
izok/errorid.py
izok/est.py
izok/parser.py
izok/position.py
izok/scaner.py
izok/token.py
izok/extension/__init__.py
izok/extension/domain.py
izok/extension/equation.py
izok/extension/model.py
izok/extension/objective.py
izok-0.0.0.dev0.dist-info/LICENSE
izok-0.0.0.dev0.dist-info/METADATA
izok-0.0.0.dev0.dist-info/WHEEL
izok-0.0.0.dev0.dist-info/top_level.txt
izok-0.0.0.dev0.dist-info/RECORD
