Metadata-Version: 2.1
Name: izok
Version: 0.0.0.dev0
Summary: Izok is an open source Python-based software package that allows you to formulate an optimization problem in an easy-to-learn and efficient modeling language similar to other modeling languages AMPL, AIMMS and GAMS, and then automatically implement it in open source software package Pyomo.
Author-email: Andrey Sergeevich Storozhenko <sto-a@yandex.ru>
Project-URL: Homepage, https://gitflic.ru/project/enom/izok
Classifier: Programming Language :: Python :: 3
Classifier: License :: OSI Approved :: BSD License
Classifier: Operating System :: OS Independent
Requires-Python: >=3.8
License-File: LICENSE
